{
 "actions": [],
 "allow_rename": 1,
 "creation": "2023-02-09 10:20:07.020773",
 "doctype": "DocType",
 "editable_grid": 1,
 "engine": "InnoDB",
 "field_order": [
  "date",
  "voucher_no",
  "amount",
  "is_generated"
 ],
 "fields": [
  {
   "allow_on_submit": 1,
   "fieldname": "date",
   "fieldtype": "Date",
   "in_list_view": 1,
   "label": "Date",
   "read_only": 1
  },
  {
   "allow_on_submit": 1,
   "fieldname": "voucher_no",
   "fieldtype": "Data",
   "in_list_view": 1,
   "label": "Voucher No",
   "read_only": 1
  },
  {
   "allow_on_submit": 1,
   "fieldname": "amount",
   "fieldtype": "Float",
   "in_list_view": 1,
   "label": "Amount",
   "read_only": 1
  },
  {
   "default": "0",
   "fieldname": "is_generated",
   "fieldtype": "Check",
   "hidden": 1,
   "label": "Is Generated"
  }
 ],
 "index_web_pages_for_search": 1,
 "istable": 1,
 "links": [],
 "modified": "2023-02-09 12:03:47.342867",
 "modified_by": "Administrator",
 "module": "Freeline",
 "name": "Rental Invoices",
 "owner": "Administrator",
 "permissions": [],
 "sort_field": "modified",
 "sort_order": "DESC"
}